Adafruit_MCP4725-1.0.2.dist-info/metadata.json
Adafruit_MCP4725-1.0.2.dist-info/METADATA
Adafruit_MCP4725-1.0.2.dist-info/RECORD
Adafruit_MCP4725-1.0.2.dist-info/WHEEL
Adafruit_MCP4725-1.0.2.dist-info/DESCRIPTION.rst
Adafruit_MCP4725-1.0.2.dist-info/dependency_links.txt
Adafruit_MCP4725-1.0.2.dist-info/top_level.txt
Adafruit_MCP4725/MCP4725.py
Adafruit_MCP4725/__init__.py
